half_adder.v
module half_adder(
    input a,
    input b,
    output sum,
    output carry
);
    assign sum = a ^ b;

    assign carry = a & b;

endmodule

module full_adder(
    input a,
    input b,
    input cin,
    output sum,
    output cout
);

wire s1;
wire c1;
wire c2;

half_adder HA1 ( .a(a), .b(b), .sum(s1), .carry(c1) );
half_adder HA2 ( .a(s1), .b(cin), .sum(sum), .carry(c2) );
assign cout = c1 | c2;

endmodule

half_adder_tb.v
`timescale 1ns/1ps
`include "half_adder.v"

module full_adder_tb;

reg a, b, cin;
wire sum, cout;

full_adder uut (
    .a(a),
    .b(b),
    .cin(cin),
    .sum(sum),
    .cout(cout)
);

initial begin
    $dumpfile(`VCD_FILE);
    $dumpvars(0, full_adder_tb);

    a=0; b=0; cin=0; #10;
    a=0; b=0; cin=1; #10;
    a=0; b=1; cin=0; #10;
    a=0; b=1; cin=1; #10;
    a=1; b=0; cin=0; #10;
    a=1; b=0; cin=1; #10;
    a=1; b=1; cin=0; #10;
    a=1; b=1; cin=1; #10;

    $finish;
end

endmodule

half_adder_tb_data_dump.vcd
$date
	Mon Feb 16 18:50:37 2026
$end
$version
	Icarus Verilog
$end
$timescale
	1ps
$end
$scope module full_adder_tb $end
$var wire 1 ! sum $end
$var wire 1 " cout $end
$var reg 1 # a $end
$var reg 1 $ b $end
$var reg 1 % cin $end
$scope module uut $end
$var wire 1 # a $end
$var wire 1 $ b $end
$var wire 1 % cin $end
$var wire 1 " cout $end
$var wire 1 ! sum $end
$var wire 1 & s1 $end
$var wire 1 ' c2 $end
$var wire 1 ( c1 $end
$scope module HA1 $end
$var wire 1 # a $end
$var wire 1 $ b $end
$var wire 1 ( carry $end
$var wire 1 & sum $end
$upscope $end
$scope module HA2 $end
$var wire 1 & a $end
$var wire 1 % b $end
$var wire 1 ' carry $end
$var wire 1 ! sum $end
$upscope $end
$upscope $end
$upscope $end
$enddefinitions $end
$comment Show the parameter values. $end
$dumpall
$end
#0
$dumpvars
0(
0'
0&
0%
0$
0#
0"
0!
$end
#10000
1!
1%
#20000
1&
0%
1$
#30000
1"
0!
1'
1%
#40000
0"
1!
0'
0%
0$
1#
#50000
1"
0!
1'
1%
#60000
0'
0&
1(
0%
1$
#70000
1!
1%
